ZC99001UNO/__init__.py
ZC99001UNO/ejemplos.py
ZC99001UNO/lineal.py
ZC99001UNO/no_lineal.py
zc99001uno-0.0.1.dist-info/METADATA
zc99001uno-0.0.1.dist-info/WHEEL
zc99001uno-0.0.1.dist-info/top_level.txt
zc99001uno-0.0.1.dist-info/RECORD
